<?xml version="1.0" encoding="windows-1251"?><Graphs_list><Graph><name>G1</name><vertexes_amount>3</vertexes_amount><vertexes>v1 v2 v3 </vertexes><vertexes_colors>-</vertexes_colors><vertexes_text>-</vertexes_text><oriented_edges>e1:v1_v2 e2:v3_v1 e3:v2_v3 </oriented_edges><not_oriented_edges>-</not_oriented_edges><edges_colors>-</edges_colors></Graph><Graph><name>G2</name><vertexes_amount>2</vertexes_amount><vertexes>v4 v5 </vertexes><vertexes_colors>-</vertexes_colors><vertexes_text>-</vertexes_text><oriented_edges>-</oriented_edges><not_oriented_edges>e1:v4_v5 </not_oriented_edges><edges_colors>-</edges_colors></Graph></Graphs_list>